odoo8_addon_mgmtsystem_hazard-8.0.1.1.0.99.dev13-nspkg.pth
odoo_addons/mgmtsystem_hazard/README.rst
odoo_addons/mgmtsystem_hazard/__init__.py
odoo_addons/mgmtsystem_hazard/__openerp__.py
odoo_addons/mgmtsystem_hazard/data/mgmtsystem_hazard_hazard.xml
odoo_addons/mgmtsystem_hazard/data/mgmtsystem_hazard_origin.xml
odoo_addons/mgmtsystem_hazard/data/mgmtsystem_hazard_probability.xml
odoo_addons/mgmtsystem_hazard/data/mgmtsystem_hazard_severity.xml
odoo_addons/mgmtsystem_hazard/data/mgmtsystem_hazard_type.xml
odoo_addons/mgmtsystem_hazard/data/mgmtsystem_hazard_usage.xml
odoo_addons/mgmtsystem_hazard/i18n/de.po
odoo_addons/mgmtsystem_hazard/i18n/es.po
odoo_addons/mgmtsystem_hazard/i18n/fr.po
odoo_addons/mgmtsystem_hazard/i18n/hr.po
odoo_addons/mgmtsystem_hazard/i18n/id.po
odoo_addons/mgmtsystem_hazard/i18n/mgmtsystem_hazard.pot
odoo_addons/mgmtsystem_hazard/i18n/nb.po
odoo_addons/mgmtsystem_hazard/i18n/pt_BR.po
odoo_addons/mgmtsystem_hazard/i18n/sl.po
odoo_addons/mgmtsystem_hazard/i18n/vi.po
odoo_addons/mgmtsystem_hazard/models/__init__.py
odoo_addons/mgmtsystem_hazard/models/mgmtsystem_hazard.py
odoo_addons/mgmtsystem_hazard/models/mgmtsystem_hazard_control_measure.py
odoo_addons/mgmtsystem_hazard/models/mgmtsystem_hazard_hazard.py
odoo_addons/mgmtsystem_hazard/models/mgmtsystem_hazard_origin.py
odoo_addons/mgmtsystem_hazard/models/mgmtsystem_hazard_probability.py
odoo_addons/mgmtsystem_hazard/models/mgmtsystem_hazard_severity.py
odoo_addons/mgmtsystem_hazard/models/mgmtsystem_hazard_test.py
odoo_addons/mgmtsystem_hazard/models/mgmtsystem_hazard_type.py
odoo_addons/mgmtsystem_hazard/models/mgmtsystem_hazard_usage.py
odoo_addons/mgmtsystem_hazard/security/ir.model.access.csv
odoo_addons/mgmtsystem_hazard/security/mgmtsystem_hazard_security.xml
odoo_addons/mgmtsystem_hazard/static/description/icon.png
odoo_addons/mgmtsystem_hazard/views/mgmtsystem_hazard.xml
odoo_addons/mgmtsystem_hazard/views/mgmtsystem_hazard_control_measure.xml
odoo8_addon_mgmtsystem_hazard-8.0.1.1.0.99.dev13.dist-info/METADATA
odoo8_addon_mgmtsystem_hazard-8.0.1.1.0.99.dev13.dist-info/WHEEL
odoo8_addon_mgmtsystem_hazard-8.0.1.1.0.99.dev13.dist-info/namespace_packages.txt
odoo8_addon_mgmtsystem_hazard-8.0.1.1.0.99.dev13.dist-info/top_level.txt
odoo8_addon_mgmtsystem_hazard-8.0.1.1.0.99.dev13.dist-info/RECORD
